{
  "kind": "codemod-console-to-logger",
  "apply": true,
  "results": [
    {
      "file": "packages/event-bus/src/config.ts",
      "changed": true,
      "applied": true
    },
    {
      "file": "packages/event-bus/src/index.ts",
      "changed": true,
      "applied": true
    },
    {
      "file": "packages/event-bus/src/validator.ts",
      "changed": true,
      "applied": true
    },
    {
      "file": "packages/otel-preset/src/index.ts",
      "changed": true,
      "applied": true
    },
    {
      "file": "packages/shared/src/error-handler.ts",
      "changed": true,
      "applied": true
    },
    {
      "file": "packages/shared/src/logger.ts",
      "changed": true,
      "applied": true
    },
    {
      "file": "packages/logger/src/adapters/node.ts",
      "changed": true,
      "applied": true
    },
    {
      "file": "packages/shared/src/auth/jwt.ts",
      "changed": true,
      "applied": true
    }
  ]
}
